himan/__init__.py
himan/pandas/__init__.py
himan/pandas/utils.py
tests/__init__.py
tests/test_reading_csv.py
tests/test_reading_excel.py
tests/test_utils.py
tests/test_writing_files.py
himan-0.0.5.dist-info/LICENSE
himan-0.0.5.dist-info/METADATA
himan-0.0.5.dist-info/WHEEL
himan-0.0.5.dist-info/top_level.txt
himan-0.0.5.dist-info/RECORD
